cr/__init__.py
cr/api.py
cr/cli.py
cr/config.py
cr/rich_utils.py
cr/ssh.py
cr/utils.py
cr/templates/settings-mariadb.py.txt
cr/templates/settings-mysql.py.txt
cr/templates/settings-postgres.py.txt
cr/templates/settings-sqlite.py.txt
cr/templates/settings-top.py.txt
cr/templates/settings-wagtail.py.txt
cr/templates/settings.py.txt
cr-1.10.dist-info/licenses/LICENSE.txt
cr-1.10.dist-info/METADATA
cr-1.10.dist-info/WHEEL
cr-1.10.dist-info/entry_points.txt
cr-1.10.dist-info/top_level.txt
cr-1.10.dist-info/RECORD
