Metadata-Version: 2.4
Name: cr
Version: 1.10
Summary: The official CodeRed Cloud command line tool.
Author-email: CodeRed LLC <info@coderedcorp.com>
License: MIT License
Project-URL: Homepage, https://www.codered.cloud/cli/
Project-URL: Source, https://github.com/coderedcorp/cr
Classifier: Environment :: Console
Classifier: Programming Language :: Python :: 3
Requires-Python: >=3.8
License-File: LICENSE.txt
Requires-Dist: certifi
Requires-Dist: paramiko==3.5.*
Requires-Dist: rich==13.9.*
Dynamic: license-file
